fraudaverse/__init__.py
fraudaverse/fraudaverse.py
fraudaverse-0.0.10.dist-info/licenses/LICENSE
fraudaverse-0.0.10.dist-info/METADATA
fraudaverse-0.0.10.dist-info/WHEEL
fraudaverse-0.0.10.dist-info/top_level.txt
fraudaverse-0.0.10.dist-info/RECORD
